gpoly/__init__.py
gpoly/gpoly.py
gpoly-0.1.4.dist-info/LICENSE
gpoly-0.1.4.dist-info/METADATA
gpoly-0.1.4.dist-info/WHEEL
gpoly-0.1.4.dist-info/entry_points.txt
gpoly-0.1.4.dist-info/top_level.txt
gpoly-0.1.4.dist-info/RECORD
