Metadata-Version: 2.1
Name: gpoly
Version: 0.1.4
Summary: Simple Earth polygon "CLI" tool
Author-email: Douglas Keller <dg.kllr.jr@gmail.com>
License:                     GNU GENERAL PUBLIC LICENSE
Project-URL: Homepage, https://github.com/dkllrjr/gpoly
Project-URL: Repository, https://github.com/dkllrjr/gpoly.git
Requires-Python: >=3.12.0
License-File: LICENSE
Requires-Dist: click
Requires-Dist: cartopy
Requires-Dist: matplotlib
Requires-Dist: numpy
Requires-Dist: scikit-image
Requires-Dist: scipy
